add_swap_space/__init__.py
add_swap_space/__main__.py
add_swap_space/add_swap_space.py
add_swap_space-7.0.0.dist-info/LICENSE
add_swap_space-7.0.0.dist-info/METADATA
add_swap_space-7.0.0.dist-info/WHEEL
add_swap_space-7.0.0.dist-info/top_level.txt
add_swap_space-7.0.0.dist-info/RECORD
