Metadata-Version: 2.1
Name: add_swap_space
Version: 7.0.0
Summary: A Python package to add swap space to a Linux system
Author-email: rb ashish <dev@rbashish.tech>
Project-URL: Homepage, https://rbashish.tech
Project-URL: Repository, https://github.com/rbashish/add-swap-space
Project-URL: Issue Tracker, https://github.com/rbashish/add-swap-space/issues
Project-URL: Changelog, https://github.com/rbashish/add-swap-space/blob/main/CHANGELOG.md
Classifier: Programming Language :: Python :: 3.6
Classifier: License :: OSI Approved :: MIT License
Classifier: Operating System :: POSIX :: Linux
Classifier: Intended Audience :: Developers
Classifier: Intended Audience :: System Administrators
Classifier: Intended Audience :: Information Technology
Classifier: Topic :: System :: Installation/Setup
Requires-Python: >=3.6
License-File: LICENSE
